MaLTHA/__main__.py
MaLTHA/convert.py
MaLTHA/database.py
MaLTHA/generate.py
MaLTHA-0.3.2.1.dist-info/LICENSE
MaLTHA-0.3.2.1.dist-info/METADATA
MaLTHA-0.3.2.1.dist-info/WHEEL
MaLTHA-0.3.2.1.dist-info/top_level.txt
MaLTHA-0.3.2.1.dist-info/RECORD
