Metadata-Version: 2.1
Name: MaLTHA
Version: 0.3.2.1
Summary: MaLTHA works as a static site generator that use Markdown format with TOML/HTML hybrid annotation.
Home-page: https://github.com/SotongDJ/MaLTHA
Author: David Soh
Author-email: ln@trth.nl
Classifier: Development Status :: 4 - Beta
Classifier: Programming Language :: Python
Classifier: Programming Language :: Python :: 3
Classifier: Programming Language :: Python :: 3.7
Classifier: Programming Language :: Python :: 3.8
Classifier: Programming Language :: Python :: 3.9
Classifier: Programming Language :: Python :: 3.10
Classifier: Programming Language :: Python :: 3.11
Classifier: Programming Language :: Python :: 3.12
Classifier: Programming Language :: Python :: Implementation :: CPython
Classifier: Programming Language :: Python :: Implementation :: PyPy
Classifier: License :: OSI Approved :: GNU General Public License v3 (GPLv3)
Classifier: Operating System :: OS Independent
License-File: LICENSE
Requires-Dist: rtoml
Requires-Dist: markdown2
Requires-Dist: Pygments
